falcon_prometheus/__init__.py
falcon_prometheus/middleware.py
falcon_prometheus-0.1.0.dist-info/METADATA
falcon_prometheus-0.1.0.dist-info/RECORD
falcon_prometheus-0.1.0.dist-info/WHEEL
falcon_prometheus-0.1.0.dist-info/top_level.txt
