Metadata-Version: 2.1
Name: falcon-prometheus
Version: 0.1.0
Summary: Falcon Framework Prometheus Middleware
Home-page: https://gitlab.com/shdh/falcon-prometheus
Author: Shawn Dhawan
Author-email: me@shdh.ca
License: MIT
Platform: UNKNOWN
Classifier: Development Status :: 3 - Alpha
Classifier: Intended Audience :: Developers
Classifier: Programming Language :: Python
Classifier: Programming Language :: Python :: 2
Classifier: Programming Language :: Python :: 2.7
Classifier: Programming Language :: Python :: 3
Classifier: Programming Language :: Python :: 3.4
Classifier: Programming Language :: Python :: 3.5
Classifier: Programming Language :: Python :: 3.6
Classifier: Programming Language :: Python :: Implementation :: CPython
Classifier: Programming Language :: Python :: Implementation :: PyPy
Classifier: Topic :: System :: Monitoring
Classifier: Topic :: Internet :: WWW/HTTP :: WSGI :: Middleware
Classifier: License :: OSI Approved :: MIT License
Requires-Dist: falcon
Requires-Dist: prometheus-client (>=0.3.1)
